LICENSE.md
MANIFEST.in
README.md
setup.cfg
setup.py
tests/test_zru.py
zru/__init__.py
zru/base.py
zru/errors.py
zru/mixin.py
zru/notification.py
zru/objects.py
zru/request.py
zru/resources.py
zru/utils.py
zru/zru.py
zru_python.egg-info/PKG-INFO
zru_python.egg-info/SOURCES.txt
zru_python.egg-info/dependency_links.txt
zru_python.egg-info/requires.txt
zru_python.egg-info/top_level.txt