Metadata-Version: 2.1
Name: zru-python
Version: 1.0.0
Summary: ZRU Python Bindings
Home-page: https://github.com/zrupay/zru-python
Download-URL: https://github.com/zrupay/zru-python/archive/v1.0.0.tar.gz
Author: ZRU
Author-email: support@zrupay.com
License: BSD
Keywords: zru,payments
Classifier: Intended Audience :: Developers
Classifier: License :: OSI Approved :: BSD License
Classifier: Operating System :: OS Independent
Classifier: Programming Language :: Python
Classifier: Programming Language :: Python :: 2
Classifier: Programming Language :: Python :: 2.7
Classifier: Programming Language :: Python :: 3
Classifier: Programming Language :: Python :: 3.3
Classifier: Programming Language :: Python :: 3.4
Classifier: Programming Language :: Python :: 3.5
Classifier: Programming Language :: Python :: 3.6
Classifier: Programming Language :: Python :: 3.7
Classifier: Programming Language :: Python :: 3.8
Classifier: Programming Language :: Python :: 3.10
Classifier: Programming Language :: Python :: 3.11
Classifier: Programming Language :: Python :: 3.12
Classifier: Programming Language :: Python :: Implementation :: PyPy
Classifier: Topic :: Software Development :: Libraries :: Python Modules
License-File: LICENSE.md
Requires-Dist: requests
Provides-Extra: test
Requires-Dist: mock; extra == "test"
Requires-Dist: coverage; extra == "test"
